{
  "schema_version": 1,
  "consumer": "weft",
  "source_repository": "HeddleCo/weft",
  "rpc_mappings": [
    {
      "rpc": "heddle.api.v1alpha1.AgentGatewayService/Connect",
      "capability": "run history/details",
      "layers": {
        "implementation": {
          "status": "planned",
          "evidence": [],
          "follow_up": null,
          "reason": "The descriptor marks this service planned."
        },
        "registration": {
          "status": "planned",
          "evidence": [],
          "follow_up": null,
          "reason": "The descriptor marks this service planned."
        }
      }
    },
    {
      "rpc": "heddle.api.v1alpha1.AgentService/ControlAgent",
      "capability": "run history/details",
      "layers": {
        "implementation": {
          "status": "planned",
          "evidence": [],
          "follow_up": null,
          "reason": "The descriptor marks this service planned."
        },
        "registration": {
          "status": "planned",
          "evidence": [],
          "follow_up": null,
          "reason": "The descriptor marks this service planned."
        }
      }
    },
    {
      "rpc": "heddle.api.v1alpha1.AgentService/DecideAgentPermission",
      "capability": "run history/details",
      "layers": {
        "implementation": {
          "status": "planned",
          "evidence": [],
          "follow_up": null,
          "reason": "The descriptor marks this service planned."
        },
        "registration": {
          "status": "planned",
          "evidence": [],
          "follow_up": null,
          "reason": "The descriptor marks this service planned."
        }
      }
    },
    {
      "rpc": "heddle.api.v1alpha1.AgentService/DeleteHarnessPreference",
      "capability": "run history/details",
      "layers": {
        "implementation": {
          "status": "planned",
          "evidence": [],
          "follow_up": null,
          "reason": "The descriptor marks this service planned."
        },
        "registration": {
          "status": "planned",
          "evidence": [],
          "follow_up": null,
          "reason": "The descriptor marks this service planned."
        }
      }
    },
    {
      "rpc": "heddle.api.v1alpha1.AgentService/GetAgentCommand",
      "capability": "run history/details",
      "layers": {
        "implementation": {
          "status": "planned",
          "evidence": [],
          "follow_up": null,
          "reason": "The descriptor marks this service planned."
        },
        "registration": {
          "status": "planned",
          "evidence": [],
          "follow_up": null,
          "reason": "The descriptor marks this service planned."
        }
      }
    },
    {
      "rpc": "heddle.api.v1alpha1.AgentService/GetAgentPolicy",
      "capability": "run history/details",
      "layers": {
        "implementation": {
          "status": "planned",
          "evidence": [],
          "follow_up": null,
          "reason": "The descriptor marks this service planned."
        },
        "registration": {
          "status": "planned",
          "evidence": [],
          "follow_up": null,
          "reason": "The descriptor marks this service planned."
        }
      }
    },
    {
      "rpc": "heddle.api.v1alpha1.AgentService/GetAgentRun",
      "capability": "run history/details",
      "layers": {
        "implementation": {
          "status": "planned",
          "evidence": [],
          "follow_up": null,
          "reason": "The descriptor marks this service planned."
        },
        "registration": {
          "status": "planned",
          "evidence": [],
          "follow_up": null,
          "reason": "The descriptor marks this service planned."
        }
      }
    },
    {
      "rpc": "heddle.api.v1alpha1.AgentService/ListAgentRuns",
      "capability": "run history/details",
      "layers": {
        "implementation": {
          "status": "planned",
          "evidence": [],
          "follow_up": null,
          "reason": "The descriptor marks this service planned."
        },
        "registration": {
          "status": "planned",
          "evidence": [],
          "follow_up": null,
          "reason": "The descriptor marks this service planned."
        }
      }
    },
    {
      "rpc": "heddle.api.v1alpha1.AgentService/ListAgentTimelineEvents",
      "capability": "run history/details",
      "layers": {
        "implementation": {
          "status": "planned",
          "evidence": [],
          "follow_up": null,
          "reason": "The descriptor marks this service planned."
        },
        "registration": {
          "status": "planned",
          "evidence": [],
          "follow_up": null,
          "reason": "The descriptor marks this service planned."
        }
      }
    },
    {
      "rpc": "heddle.api.v1alpha1.AgentService/ListHarnessPreferences",
      "capability": "run history/details",
      "layers": {
        "implementation": {
          "status": "planned",
          "evidence": [],
          "follow_up": null,
          "reason": "The descriptor marks this service planned."
        },
        "registration": {
          "status": "planned",
          "evidence": [],
          "follow_up": null,
          "reason": "The descriptor marks this service planned."
        }
      }
    },
    {
      "rpc": "heddle.api.v1alpha1.AgentService/UpdateAgentPolicy",
      "capability": "run history/details",
      "layers": {
        "implementation": {
          "status": "planned",
          "evidence": [],
          "follow_up": null,
          "reason": "The descriptor marks this service planned."
        },
        "registration": {
          "status": "planned",
          "evidence": [],
          "follow_up": null,
          "reason": "The descriptor marks this service planned."
        }
      }
    },
    {
      "rpc": "heddle.api.v1alpha1.AgentService/WatchAgentRun",
      "capability": "run history/details",
      "layers": {
        "implementation": {
          "status": "planned",
          "evidence": [],
          "follow_up": null,
          "reason": "The descriptor marks this service planned."
        },
        "registration": {
          "status": "planned",
          "evidence": [],
          "follow_up": null,
          "reason": "The descriptor marks this service planned."
        }
      }
    },
    {
      "rpc": "heddle.api.v1alpha1.AttentionService/GetFeedSnapshot",
      "capability": "attention feed",
      "layers": {
        "implementation": {
          "status": "shipped",
          "evidence": [
            "crates/weft-server/src/server/grpc_hosted_impl/feed.rs:GetFeedSnapshot"
          ],
          "follow_up": null
        },
        "registration": {
          "status": "shipped",
          "evidence": [
            "crates/weft-server/src/serve.rs:FeedServiceServer::new"
          ],
          "follow_up": null
        }
      }
    },
    {
      "rpc": "heddle.api.v1alpha1.AttentionService/RecordInteraction",
      "capability": "attention feed",
      "layers": {
        "implementation": {
          "status": "shipped",
          "evidence": [
            "crates/weft-server/src/server/grpc_hosted_impl/feed.rs:RecordInteraction"
          ],
          "follow_up": null
        },
        "registration": {
          "status": "shipped",
          "evidence": [
            "crates/weft-server/src/serve.rs:FeedServiceServer::new"
          ],
          "follow_up": null
        }
      }
    },
    {
      "rpc": "heddle.api.v1alpha1.AttentionService/StreamFeed",
      "capability": "attention feed",
      "layers": {
        "implementation": {
          "status": "shipped",
          "evidence": [
            "crates/weft-server/src/server/grpc_hosted_impl/feed.rs:StreamFeed"
          ],
          "follow_up": null
        },
        "registration": {
          "status": "shipped",
          "evidence": [
            "crates/weft-server/src/serve.rs:FeedServiceServer::new"
          ],
          "follow_up": null
        }
      }
    },
    {
      "rpc": "heddle.api.v1alpha1.AttentionService/UpdateFeedItem",
      "capability": "attention feed",
      "layers": {
        "implementation": {
          "status": "shipped",
          "evidence": [
            "crates/weft-server/src/server/grpc_hosted_impl/feed.rs:UpdateFeedItem"
          ],
          "follow_up": null
        },
        "registration": {
          "status": "shipped",
          "evidence": [
            "crates/weft-server/src/serve.rs:FeedServiceServer::new"
          ],
          "follow_up": null
        }
      }
    },
    {
      "rpc": "heddle.api.v1alpha1.CollaborationService/AppendTurn",
      "capability": "collaboration",
      "layers": {
        "implementation": {
          "status": "shipped",
          "evidence": [
            "crates/weft-server/src/server/grpc_hosted_impl/discussion.rs:AppendTurn"
          ],
          "follow_up": null
        },
        "registration": {
          "status": "shipped",
          "evidence": [
            "crates/weft-server/src/serve.rs:DiscussionServiceServer::new"
          ],
          "follow_up": null
        }
      }
    },
    {
      "rpc": "heddle.api.v1alpha1.CollaborationService/ListByState",
      "capability": "collaboration",
      "layers": {
        "implementation": {
          "status": "shipped",
          "evidence": [
            "crates/weft-server/src/server/grpc_hosted_impl/discussion.rs:ListByState"
          ],
          "follow_up": null
        },
        "registration": {
          "status": "shipped",
          "evidence": [
            "crates/weft-server/src/serve.rs:DiscussionServiceServer::new"
          ],
          "follow_up": null
        }
      }
    },
    {
      "rpc": "heddle.api.v1alpha1.CollaborationService/ListBySymbol",
      "capability": "collaboration",
      "layers": {
        "implementation": {
          "status": "shipped",
          "evidence": [
            "crates/weft-server/src/server/grpc_hosted_impl/discussion.rs:ListBySymbol"
          ],
          "follow_up": null
        },
        "registration": {
          "status": "shipped",
          "evidence": [
            "crates/weft-server/src/serve.rs:DiscussionServiceServer::new"
          ],
          "follow_up": null
        }
      }
    },
    {
      "rpc": "heddle.api.v1alpha1.CollaborationService/OpenDiscussion",
      "capability": "collaboration",
      "layers": {
        "implementation": {
          "status": "shipped",
          "evidence": [
            "crates/weft-server/src/server/grpc_hosted_impl/discussion.rs:OpenDiscussion"
          ],
          "follow_up": null
        },
        "registration": {
          "status": "shipped",
          "evidence": [
            "crates/weft-server/src/serve.rs:DiscussionServiceServer::new"
          ],
          "follow_up": null
        }
      }
    },
    {
      "rpc": "heddle.api.v1alpha1.CollaborationService/ResolveDiscussion",
      "capability": "collaboration",
      "layers": {
        "implementation": {
          "status": "shipped",
          "evidence": [
            "crates/weft-server/src/server/grpc_hosted_impl/discussion.rs:ResolveDiscussion"
          ],
          "follow_up": null
        },
        "registration": {
          "status": "shipped",
          "evidence": [
            "crates/weft-server/src/serve.rs:DiscussionServiceServer::new"
          ],
          "follow_up": null
        }
      }
    },
    {
      "rpc": "heddle.api.v1alpha1.IdentityService/ApproveDeviceAuthorization",
      "capability": "identity and credentials",
      "layers": {
        "implementation": {
          "status": "shipped",
          "evidence": [
            "crates/weft-server/src/server/grpc_hosted_impl/auth.rs:ApproveDeviceAuthorization"
          ],
          "follow_up": null
        },
        "registration": {
          "status": "shipped",
          "evidence": [
            "crates/weft-server/src/serve.rs:AuthServiceServer::new"
          ],
          "follow_up": null
        }
      }
    },
    {
      "rpc": "heddle.api.v1alpha1.IdentityService/BeginWebAuthnAuthentication",
      "capability": "identity and credentials",
      "layers": {
        "implementation": {
          "status": "shipped",
          "evidence": [
            "crates/weft-server/src/server/grpc_hosted_impl/auth.rs:BeginWebAuthnAuthentication"
          ],
          "follow_up": null
        },
        "registration": {
          "status": "shipped",
          "evidence": [
            "crates/weft-server/src/serve.rs:AuthServiceServer::new"
          ],
          "follow_up": null
        }
      }
    },
    {
      "rpc": "heddle.api.v1alpha1.IdentityService/BeginWebAuthnRegistration",
      "capability": "identity and credentials",
      "layers": {
        "implementation": {
          "status": "shipped",
          "evidence": [
            "crates/weft-server/src/server/grpc_hosted_impl/auth.rs:BeginWebAuthnRegistration"
          ],
          "follow_up": null
        },
        "registration": {
          "status": "shipped",
          "evidence": [
            "crates/weft-server/src/serve.rs:AuthServiceServer::new"
          ],
          "follow_up": null
        }
      }
    },
    {
      "rpc": "heddle.api.v1alpha1.IdentityService/CreateDeviceAuthorization",
      "capability": "identity and credentials",
      "layers": {
        "implementation": {
          "status": "shipped",
          "evidence": [
            "crates/weft-server/src/server/grpc_hosted_impl/auth.rs:CreateDeviceAuthorization"
          ],
          "follow_up": null
        },
        "registration": {
          "status": "shipped",
          "evidence": [
            "crates/weft-server/src/serve.rs:AuthServiceServer::new"
          ],
          "follow_up": null
        }
      }
    },
    {
      "rpc": "heddle.api.v1alpha1.IdentityService/CreateServiceAccount",
      "capability": "identity and credentials",
      "layers": {
        "implementation": {
          "status": "shipped",
          "evidence": [
            "crates/weft-server/src/server/grpc_hosted_impl/auth.rs:CreateServiceAccount"
          ],
          "follow_up": null
        },
        "registration": {
          "status": "shipped",
          "evidence": [
            "crates/weft-server/src/serve.rs:AuthServiceServer::new"
          ],
          "follow_up": null
        }
      }
    },
    {
      "rpc": "heddle.api.v1alpha1.IdentityService/ExchangeDeviceAuthorization",
      "capability": "identity and credentials",
      "layers": {
        "implementation": {
          "status": "shipped",
          "evidence": [
            "crates/weft-server/src/server/grpc_hosted_impl/auth.rs:ExchangeDeviceAuthorization"
          ],
          "follow_up": null
        },
        "registration": {
          "status": "shipped",
          "evidence": [
            "crates/weft-server/src/serve.rs:AuthServiceServer::new"
          ],
          "follow_up": null
        }
      }
    },
    {
      "rpc": "heddle.api.v1alpha1.IdentityService/FinishWebAuthnAuthentication",
      "capability": "identity and credentials",
      "layers": {
        "implementation": {
          "status": "shipped",
          "evidence": [
            "crates/weft-server/src/server/grpc_hosted_impl/auth.rs:FinishWebAuthnAuthentication"
          ],
          "follow_up": null
        },
        "registration": {
          "status": "shipped",
          "evidence": [
            "crates/weft-server/src/serve.rs:AuthServiceServer::new"
          ],
          "follow_up": null
        }
      }
    },
    {
      "rpc": "heddle.api.v1alpha1.IdentityService/GetInvitationSummary",
      "capability": "identity and credentials",
      "layers": {
        "implementation": {
          "status": "shipped",
          "evidence": [
            "crates/weft-server/src/server/grpc_hosted_impl/auth.rs:GetInvitationSummary"
          ],
          "follow_up": null
        },
        "registration": {
          "status": "shipped",
          "evidence": [
            "crates/weft-server/src/serve.rs:AuthServiceServer::new"
          ],
          "follow_up": null
        }
      }
    },
    {
      "rpc": "heddle.api.v1alpha1.IdentityService/IntrospectCredential",
      "capability": "identity and credentials",
      "layers": {
        "implementation": {
          "status": "shipped",
          "evidence": [
            "crates/weft-server/src/server/grpc_hosted_impl/auth.rs:IntrospectCredential"
          ],
          "follow_up": null
        },
        "registration": {
          "status": "shipped",
          "evidence": [
            "crates/weft-server/src/serve.rs:AuthServiceServer::new"
          ],
          "follow_up": null
        }
      }
    },
    {
      "rpc": "heddle.api.v1alpha1.IdentityService/IssuePresenceToken",
      "capability": "identity and credentials",
      "layers": {
        "implementation": {
          "status": "shipped",
          "evidence": [
            "crates/weft-server/src/server/grpc_hosted_impl/auth.rs:IssuePresenceToken"
          ],
          "follow_up": null
        },
        "registration": {
          "status": "shipped",
          "evidence": [
            "crates/weft-server/src/serve.rs:AuthServiceServer::new"
          ],
          "follow_up": null
        }
      }
    },
    {
      "rpc": "heddle.api.v1alpha1.IdentityService/IssueServiceAccountCredential",
      "capability": "identity and credentials",
      "layers": {
        "implementation": {
          "status": "shipped",
          "evidence": [
            "crates/weft-server/src/server/grpc_hosted_impl/auth.rs:IssueServiceAccountCredential"
          ],
          "follow_up": null
        },
        "registration": {
          "status": "shipped",
          "evidence": [
            "crates/weft-server/src/serve.rs:AuthServiceServer::new"
          ],
          "follow_up": null
        }
      }
    },
    {
      "rpc": "heddle.api.v1alpha1.IdentityService/LinkOAuthIdentity",
      "capability": "identity and credentials",
      "layers": {
        "implementation": {
          "status": "shipped",
          "evidence": [
            "crates/weft-server/src/server/grpc_hosted_impl/auth.rs:LinkOAuthIdentity"
          ],
          "follow_up": null
        },
        "registration": {
          "status": "shipped",
          "evidence": [
            "crates/weft-server/src/serve.rs:AuthServiceServer::new"
          ],
          "follow_up": null
        }
      }
    },
    {
      "rpc": "heddle.api.v1alpha1.IdentityService/ListScopeCapabilities",
      "capability": "identity and credentials",
      "layers": {
        "implementation": {
          "status": "shipped",
          "evidence": [
            "crates/weft-server/src/server/grpc_hosted_impl/auth.rs:ListScopeCapabilities"
          ],
          "follow_up": null
        },
        "registration": {
          "status": "shipped",
          "evidence": [
            "crates/weft-server/src/serve.rs:AuthServiceServer::new"
          ],
          "follow_up": null
        }
      }
    },
    {
      "rpc": "heddle.api.v1alpha1.IdentityService/ListServiceAccounts",
      "capability": "identity and credentials",
      "layers": {
        "implementation": {
          "status": "shipped",
          "evidence": [
            "crates/weft-server/src/server/grpc_hosted_impl/auth.rs:ListServiceAccounts"
          ],
          "follow_up": null
        },
        "registration": {
          "status": "shipped",
          "evidence": [
            "crates/weft-server/src/serve.rs:AuthServiceServer::new"
          ],
          "follow_up": null
        }
      }
    },
    {
      "rpc": "heddle.api.v1alpha1.IdentityService/ListSessions",
      "capability": "identity and credentials",
      "layers": {
        "implementation": {
          "status": "shipped",
          "evidence": [
            "crates/weft-server/src/server/grpc_hosted_impl/auth.rs:ListSessions"
          ],
          "follow_up": null
        },
        "registration": {
          "status": "shipped",
          "evidence": [
            "crates/weft-server/src/serve.rs:AuthServiceServer::new"
          ],
          "follow_up": null
        }
      }
    },
    {
      "rpc": "heddle.api.v1alpha1.IdentityService/MintAnonBiscuit",
      "capability": "identity and credentials",
      "layers": {
        "implementation": {
          "status": "shipped",
          "evidence": [
            "crates/weft-server/src/server/grpc_hosted_impl/auth.rs:MintAnonBiscuit"
          ],
          "follow_up": null
        },
        "registration": {
          "status": "shipped",
          "evidence": [
            "crates/weft-server/src/serve.rs:AuthServiceServer::new"
          ],
          "follow_up": null
        }
      }
    },
    {
      "rpc": "heddle.api.v1alpha1.IdentityService/MintBiscuit",
      "capability": "identity and credentials",
      "layers": {
        "implementation": {
          "status": "shipped",
          "evidence": [
            "crates/weft-server/src/server/grpc_hosted_impl/auth.rs:MintBiscuit"
          ],
          "follow_up": null
        },
        "registration": {
          "status": "shipped",
          "evidence": [
            "crates/weft-server/src/serve.rs:AuthServiceServer::new"
          ],
          "follow_up": null
        }
      }
    },
    {
      "rpc": "heddle.api.v1alpha1.IdentityService/RegisterPublicKey",
      "capability": "identity and credentials",
      "layers": {
        "implementation": {
          "status": "shipped",
          "evidence": [
            "crates/weft-server/src/server/grpc_hosted_impl/auth.rs:RegisterPublicKey"
          ],
          "follow_up": null
        },
        "registration": {
          "status": "shipped",
          "evidence": [
            "crates/weft-server/src/serve.rs:AuthServiceServer::new"
          ],
          "follow_up": null
        }
      }
    },
    {
      "rpc": "heddle.api.v1alpha1.IdentityService/RevokeCredential",
      "capability": "identity and credentials",
      "layers": {
        "implementation": {
          "status": "shipped",
          "evidence": [
            "crates/weft-server/src/server/grpc_hosted_impl/auth.rs:RevokeCredential"
          ],
          "follow_up": null
        },
        "registration": {
          "status": "shipped",
          "evidence": [
            "crates/weft-server/src/serve.rs:AuthServiceServer::new"
          ],
          "follow_up": null
        }
      }
    },
    {
      "rpc": "heddle.api.v1alpha1.IdentityService/RevokeServiceAccount",
      "capability": "identity and credentials",
      "layers": {
        "implementation": {
          "status": "shipped",
          "evidence": [
            "crates/weft-server/src/server/grpc_hosted_impl/auth.rs:RevokeServiceAccount"
          ],
          "follow_up": null
        },
        "registration": {
          "status": "shipped",
          "evidence": [
            "crates/weft-server/src/serve.rs:AuthServiceServer::new"
          ],
          "follow_up": null
        }
      }
    },
    {
      "rpc": "heddle.api.v1alpha1.IdentityService/RevokeSession",
      "capability": "identity and credentials",
      "layers": {
        "implementation": {
          "status": "shipped",
          "evidence": [
            "crates/weft-server/src/server/grpc_hosted_impl/auth.rs:RevokeSession"
          ],
          "follow_up": null
        },
        "registration": {
          "status": "shipped",
          "evidence": [
            "crates/weft-server/src/serve.rs:AuthServiceServer::new"
          ],
          "follow_up": null
        }
      }
    },
    {
      "rpc": "heddle.api.v1alpha1.IdentityService/RotateCredential",
      "capability": "identity and credentials",
      "layers": {
        "implementation": {
          "status": "shipped",
          "evidence": [
            "crates/weft-server/src/server/grpc_hosted_impl/auth.rs:RotateCredential"
          ],
          "follow_up": null
        },
        "registration": {
          "status": "shipped",
          "evidence": [
            "crates/weft-server/src/serve.rs:AuthServiceServer::new"
          ],
          "follow_up": null
        }
      }
    },
    {
      "rpc": "heddle.api.v1alpha1.IdentityService/StoreProviderToken",
      "capability": "identity and credentials",
      "layers": {
        "implementation": {
          "status": "shipped",
          "evidence": [
            "crates/weft-server/src/server/grpc_hosted_impl/auth.rs:StoreProviderToken"
          ],
          "follow_up": null
        },
        "registration": {
          "status": "shipped",
          "evidence": [
            "crates/weft-server/src/serve.rs:AuthServiceServer::new"
          ],
          "follow_up": null
        }
      }
    },
    {
      "rpc": "heddle.api.v1alpha1.IdentityService/VerifySignupEmail",
      "capability": "identity and credentials",
      "layers": {
        "implementation": {
          "status": "shipped",
          "evidence": [
            "crates/weft-server/src/server/grpc_hosted_impl/auth.rs:VerifySignupEmail"
          ],
          "follow_up": null
        },
        "registration": {
          "status": "shipped",
          "evidence": [
            "crates/weft-server/src/serve.rs:AuthServiceServer::new"
          ],
          "follow_up": null
        }
      }
    },
    {
      "rpc": "heddle.api.v1alpha1.IdentityService/WaitForDeviceAuthorization",
      "capability": "identity and credentials",
      "layers": {
        "implementation": {
          "status": "shipped",
          "evidence": [
            "crates/weft-server/src/server/grpc_hosted_impl/auth.rs:WaitForDeviceAuthorization"
          ],
          "follow_up": null
        },
        "registration": {
          "status": "shipped",
          "evidence": [
            "crates/weft-server/src/serve.rs:AuthServiceServer::new"
          ],
          "follow_up": null
        }
      }
    },
    {
      "rpc": "heddle.api.v1alpha1.IdentityService/WhoAmI",
      "capability": "identity and credentials",
      "layers": {
        "implementation": {
          "status": "shipped",
          "evidence": [
            "crates/weft-server/src/server/grpc_hosted_impl/auth.rs:WhoAmI"
          ],
          "follow_up": null
        },
        "registration": {
          "status": "shipped",
          "evidence": [
            "crates/weft-server/src/serve.rs:AuthServiceServer::new"
          ],
          "follow_up": null
        }
      }
    },
    {
      "rpc": "heddle.api.v1alpha1.PullRequestReviewService/GetReviewAnalysisResult",
      "capability": "pull request review",
      "layers": {
        "implementation": {
          "status": "shipped",
          "evidence": [
            "crates/weft-server/src/server/grpc_hosted_impl/review.rs:GetReviewAnalysisResult"
          ],
          "follow_up": null
        },
        "registration": {
          "status": "shipped",
          "evidence": [
            "crates/weft-server/src/serve.rs:ReviewServiceServer::new"
          ],
          "follow_up": null
        }
      }
    },
    {
      "rpc": "heddle.api.v1alpha1.PullRequestReviewService/GetReviewAnalysisStatus",
      "capability": "pull request review",
      "layers": {
        "implementation": {
          "status": "shipped",
          "evidence": [
            "crates/weft-server/src/server/grpc_hosted_impl/review.rs:GetReviewAnalysisStatus"
          ],
          "follow_up": null
        },
        "registration": {
          "status": "shipped",
          "evidence": [
            "crates/weft-server/src/serve.rs:ReviewServiceServer::new"
          ],
          "follow_up": null
        }
      }
    },
    {
      "rpc": "heddle.api.v1alpha1.PullRequestReviewService/StartReviewAnalysis",
      "capability": "pull request review",
      "layers": {
        "implementation": {
          "status": "shipped",
          "evidence": [
            "crates/weft-server/src/server/grpc_hosted_impl/review.rs:StartReviewAnalysis"
          ],
          "follow_up": null
        },
        "registration": {
          "status": "shipped",
          "evidence": [
            "crates/weft-server/src/serve.rs:ReviewServiceServer::new"
          ],
          "follow_up": null
        }
      }
    },
    {
      "rpc": "heddle.api.v1alpha1.RegistryService/AttachChild",
      "capability": "spool administration",
      "layers": {
        "implementation": {
          "status": "shipped",
          "evidence": [
            "crates/weft-server/src/server/grpc_hosted_impl/user.rs:AttachChild"
          ],
          "follow_up": null
        },
        "registration": {
          "status": "shipped",
          "evidence": [
            "crates/weft-server/src/serve.rs:HostedUserServiceServer::new"
          ],
          "follow_up": null
        }
      }
    },
    {
      "rpc": "heddle.api.v1alpha1.RegistryService/CreateGrant",
      "capability": "spool administration",
      "layers": {
        "implementation": {
          "status": "shipped",
          "evidence": [
            "crates/weft-server/src/server/grpc_hosted_impl/user.rs:CreateGrant"
          ],
          "follow_up": null
        },
        "registration": {
          "status": "shipped",
          "evidence": [
            "crates/weft-server/src/serve.rs:HostedUserServiceServer::new"
          ],
          "follow_up": null
        }
      }
    },
    {
      "rpc": "heddle.api.v1alpha1.RegistryService/CreateInvitation",
      "capability": "spool administration",
      "layers": {
        "implementation": {
          "status": "shipped",
          "evidence": [
            "crates/weft-server/src/server/grpc_hosted_impl/user.rs:CreateInvitation"
          ],
          "follow_up": null
        },
        "registration": {
          "status": "shipped",
          "evidence": [
            "crates/weft-server/src/serve.rs:HostedUserServiceServer::new"
          ],
          "follow_up": null
        }
      }
    },
    {
      "rpc": "heddle.api.v1alpha1.RegistryService/CreateNamespace",
      "capability": "spool administration",
      "layers": {
        "implementation": {
          "status": "shipped",
          "evidence": [
            "crates/weft-server/src/server/grpc_hosted_impl/user.rs:CreateNamespace"
          ],
          "follow_up": null
        },
        "registration": {
          "status": "shipped",
          "evidence": [
            "crates/weft-server/src/serve.rs:HostedUserServiceServer::new"
          ],
          "follow_up": null
        }
      }
    },
    {
      "rpc": "heddle.api.v1alpha1.RegistryService/CreateRepository",
      "capability": "spool administration",
      "layers": {
        "implementation": {
          "status": "shipped",
          "evidence": [
            "crates/weft-server/src/server/grpc_hosted_impl/user.rs:CreateRepository"
          ],
          "follow_up": null
        },
        "registration": {
          "status": "shipped",
          "evidence": [
            "crates/weft-server/src/serve.rs:HostedUserServiceServer::new"
          ],
          "follow_up": null
        }
      }
    },
    {
      "rpc": "heddle.api.v1alpha1.RegistryService/DeleteBookmark",
      "capability": "spool administration",
      "layers": {
        "implementation": {
          "status": "shipped",
          "evidence": [
            "crates/weft-server/src/server/grpc_hosted_impl/user.rs:DeleteBookmark"
          ],
          "follow_up": null
        },
        "registration": {
          "status": "shipped",
          "evidence": [
            "crates/weft-server/src/serve.rs:HostedUserServiceServer::new"
          ],
          "follow_up": null
        }
      }
    },
    {
      "rpc": "heddle.api.v1alpha1.RegistryService/DeleteGrant",
      "capability": "spool administration",
      "layers": {
        "implementation": {
          "status": "shipped",
          "evidence": [
            "crates/weft-server/src/server/grpc_hosted_impl/user.rs:DeleteGrant"
          ],
          "follow_up": null
        },
        "registration": {
          "status": "shipped",
          "evidence": [
            "crates/weft-server/src/serve.rs:HostedUserServiceServer::new"
          ],
          "follow_up": null
        }
      }
    },
    {
      "rpc": "heddle.api.v1alpha1.RegistryService/DeleteNamespace",
      "capability": "spool administration",
      "layers": {
        "implementation": {
          "status": "shipped",
          "evidence": [
            "crates/weft-server/src/server/grpc_hosted_impl/user.rs:DeleteNamespace"
          ],
          "follow_up": null
        },
        "registration": {
          "status": "shipped",
          "evidence": [
            "crates/weft-server/src/serve.rs:HostedUserServiceServer::new"
          ],
          "follow_up": null
        }
      }
    },
    {
      "rpc": "heddle.api.v1alpha1.RegistryService/DeleteRepository",
      "capability": "spool administration",
      "layers": {
        "implementation": {
          "status": "shipped",
          "evidence": [
            "crates/weft-server/src/server/grpc_hosted_impl/user.rs:DeleteRepository"
          ],
          "follow_up": null
        },
        "registration": {
          "status": "shipped",
          "evidence": [
            "crates/weft-server/src/serve.rs:HostedUserServiceServer::new"
          ],
          "follow_up": null
        }
      }
    },
    {
      "rpc": "heddle.api.v1alpha1.RegistryService/DetachChild",
      "capability": "spool administration",
      "layers": {
        "implementation": {
          "status": "shipped",
          "evidence": [
            "crates/weft-server/src/server/grpc_hosted_impl/user.rs:DetachChild"
          ],
          "follow_up": null
        },
        "registration": {
          "status": "shipped",
          "evidence": [
            "crates/weft-server/src/serve.rs:HostedUserServiceServer::new"
          ],
          "follow_up": null
        }
      }
    },
    {
      "rpc": "heddle.api.v1alpha1.RegistryService/GetCurrentUserNamespace",
      "capability": "spool administration",
      "layers": {
        "implementation": {
          "status": "shipped",
          "evidence": [
            "crates/weft-server/src/server/grpc_hosted_impl/user.rs:GetCurrentUserNamespace"
          ],
          "follow_up": null
        },
        "registration": {
          "status": "shipped",
          "evidence": [
            "crates/weft-server/src/serve.rs:HostedUserServiceServer::new"
          ],
          "follow_up": null
        }
      }
    },
    {
      "rpc": "heddle.api.v1alpha1.RegistryService/GetSpool",
      "capability": "spool administration",
      "layers": {
        "implementation": {
          "status": "shipped",
          "evidence": [
            "crates/weft-server/src/server/grpc_hosted_impl/user.rs:GetSpool"
          ],
          "follow_up": null
        },
        "registration": {
          "status": "shipped",
          "evidence": [
            "crates/weft-server/src/serve.rs:HostedUserServiceServer::new"
          ],
          "follow_up": null
        }
      }
    },
    {
      "rpc": "heddle.api.v1alpha1.RegistryService/GrantSupportAccess",
      "capability": "spool administration",
      "layers": {
        "implementation": {
          "status": "shipped",
          "evidence": [
            "crates/weft-server/src/server/grpc_hosted_impl/user.rs:GrantSupportAccess"
          ],
          "follow_up": null
        },
        "registration": {
          "status": "shipped",
          "evidence": [
            "crates/weft-server/src/serve.rs:HostedUserServiceServer::new"
          ],
          "follow_up": null
        }
      }
    },
    {
      "rpc": "heddle.api.v1alpha1.RegistryService/ListBookmarks",
      "capability": "spool administration",
      "layers": {
        "implementation": {
          "status": "shipped",
          "evidence": [
            "crates/weft-server/src/server/grpc_hosted_impl/user.rs:ListBookmarks"
          ],
          "follow_up": null
        },
        "registration": {
          "status": "shipped",
          "evidence": [
            "crates/weft-server/src/serve.rs:HostedUserServiceServer::new"
          ],
          "follow_up": null
        }
      }
    },
    {
      "rpc": "heddle.api.v1alpha1.RegistryService/ListChildren",
      "capability": "spool administration",
      "layers": {
        "implementation": {
          "status": "shipped",
          "evidence": [
            "crates/weft-server/src/server/grpc_hosted_impl/user.rs:ListChildren"
          ],
          "follow_up": null
        },
        "registration": {
          "status": "shipped",
          "evidence": [
            "crates/weft-server/src/serve.rs:HostedUserServiceServer::new"
          ],
          "follow_up": null
        }
      }
    },
    {
      "rpc": "heddle.api.v1alpha1.RegistryService/ListGrants",
      "capability": "spool administration",
      "layers": {
        "implementation": {
          "status": "shipped",
          "evidence": [
            "crates/weft-server/src/server/grpc_hosted_impl/user.rs:ListGrants"
          ],
          "follow_up": null
        },
        "registration": {
          "status": "shipped",
          "evidence": [
            "crates/weft-server/src/serve.rs:HostedUserServiceServer::new"
          ],
          "follow_up": null
        }
      }
    },
    {
      "rpc": "heddle.api.v1alpha1.RegistryService/ListInvitations",
      "capability": "spool administration",
      "layers": {
        "implementation": {
          "status": "shipped",
          "evidence": [
            "crates/weft-server/src/server/grpc_hosted_impl/user.rs:ListInvitations"
          ],
          "follow_up": null
        },
        "registration": {
          "status": "shipped",
          "evidence": [
            "crates/weft-server/src/serve.rs:HostedUserServiceServer::new"
          ],
          "follow_up": null
        }
      }
    },
    {
      "rpc": "heddle.api.v1alpha1.RegistryService/ListMembers",
      "capability": "spool administration",
      "layers": {
        "implementation": {
          "status": "shipped",
          "evidence": [
            "crates/weft-server/src/server/grpc_hosted_impl/user.rs:ListMembers"
          ],
          "follow_up": null
        },
        "registration": {
          "status": "shipped",
          "evidence": [
            "crates/weft-server/src/serve.rs:HostedUserServiceServer::new"
          ],
          "follow_up": null
        }
      }
    },
    {
      "rpc": "heddle.api.v1alpha1.RegistryService/ListSpools",
      "capability": "spool administration",
      "layers": {
        "implementation": {
          "status": "shipped",
          "evidence": [
            "crates/weft-server/src/server/grpc_hosted_impl/user.rs:ListSpools"
          ],
          "follow_up": null
        },
        "registration": {
          "status": "shipped",
          "evidence": [
            "crates/weft-server/src/serve.rs:HostedUserServiceServer::new"
          ],
          "follow_up": null
        }
      }
    },
    {
      "rpc": "heddle.api.v1alpha1.RegistryService/ListSupportAccessGrants",
      "capability": "spool administration",
      "layers": {
        "implementation": {
          "status": "shipped",
          "evidence": [
            "crates/weft-server/src/server/grpc_hosted_impl/user.rs:ListSupportAccessGrants"
          ],
          "follow_up": null
        },
        "registration": {
          "status": "shipped",
          "evidence": [
            "crates/weft-server/src/serve.rs:HostedUserServiceServer::new"
          ],
          "follow_up": null
        }
      }
    },
    {
      "rpc": "heddle.api.v1alpha1.RegistryService/ListWorktrees",
      "capability": "spool administration",
      "layers": {
        "implementation": {
          "status": "shipped",
          "evidence": [
            "crates/weft-server/src/server/grpc_hosted_impl/user.rs:ListWorktrees"
          ],
          "follow_up": null
        },
        "registration": {
          "status": "shipped",
          "evidence": [
            "crates/weft-server/src/serve.rs:HostedUserServiceServer::new"
          ],
          "follow_up": null
        }
      }
    },
    {
      "rpc": "heddle.api.v1alpha1.RegistryService/ResolveMonorepo",
      "capability": "spool administration",
      "layers": {
        "implementation": {
          "status": "shipped",
          "evidence": [
            "crates/weft-server/src/server/grpc_hosted_impl/user.rs:ResolveMonorepo"
          ],
          "follow_up": null
        },
        "registration": {
          "status": "shipped",
          "evidence": [
            "crates/weft-server/src/serve.rs:HostedUserServiceServer::new"
          ],
          "follow_up": null
        }
      }
    },
    {
      "rpc": "heddle.api.v1alpha1.RegistryService/ResolveSubjects",
      "capability": "spool administration",
      "layers": {
        "implementation": {
          "status": "shipped",
          "evidence": [
            "crates/weft-server/src/server/grpc_hosted_impl/user.rs:ResolveSubjects"
          ],
          "follow_up": null
        },
        "registration": {
          "status": "shipped",
          "evidence": [
            "crates/weft-server/src/serve.rs:HostedUserServiceServer::new"
          ],
          "follow_up": null
        }
      }
    },
    {
      "rpc": "heddle.api.v1alpha1.RegistryService/RevokeInvitation",
      "capability": "spool administration",
      "layers": {
        "implementation": {
          "status": "shipped",
          "evidence": [
            "crates/weft-server/src/server/grpc_hosted_impl/user.rs:RevokeInvitation"
          ],
          "follow_up": null
        },
        "registration": {
          "status": "shipped",
          "evidence": [
            "crates/weft-server/src/serve.rs:HostedUserServiceServer::new"
          ],
          "follow_up": null
        }
      }
    },
    {
      "rpc": "heddle.api.v1alpha1.RegistryService/RevokeSupportAccess",
      "capability": "spool administration",
      "layers": {
        "implementation": {
          "status": "shipped",
          "evidence": [
            "crates/weft-server/src/server/grpc_hosted_impl/user.rs:RevokeSupportAccess"
          ],
          "follow_up": null
        },
        "registration": {
          "status": "shipped",
          "evidence": [
            "crates/weft-server/src/serve.rs:HostedUserServiceServer::new"
          ],
          "follow_up": null
        }
      }
    },
    {
      "rpc": "heddle.api.v1alpha1.RegistryService/SetNamespaceVisibility",
      "capability": "spool administration",
      "layers": {
        "implementation": {
          "status": "shipped",
          "evidence": [
            "crates/weft-server/src/server/grpc_hosted_impl/user.rs:SetNamespaceVisibility"
          ],
          "follow_up": null
        },
        "registration": {
          "status": "shipped",
          "evidence": [
            "crates/weft-server/src/serve.rs:HostedUserServiceServer::new"
          ],
          "follow_up": null
        }
      }
    },
    {
      "rpc": "heddle.api.v1alpha1.RegistryService/SetSpoolVisibility",
      "capability": "spool administration",
      "layers": {
        "implementation": {
          "status": "shipped",
          "evidence": [
            "crates/weft-server/src/server/grpc_hosted_impl/user.rs:SetSpoolVisibility"
          ],
          "follow_up": null
        },
        "registration": {
          "status": "shipped",
          "evidence": [
            "crates/weft-server/src/serve.rs:HostedUserServiceServer::new"
          ],
          "follow_up": null
        }
      }
    },
    {
      "rpc": "heddle.api.v1alpha1.RegistryService/UpdateGrant",
      "capability": "spool administration",
      "layers": {
        "implementation": {
          "status": "shipped",
          "evidence": [
            "crates/weft-server/src/server/grpc_hosted_impl/user.rs:UpdateGrant"
          ],
          "follow_up": null
        },
        "registration": {
          "status": "shipped",
          "evidence": [
            "crates/weft-server/src/serve.rs:HostedUserServiceServer::new"
          ],
          "follow_up": null
        }
      }
    },
    {
      "rpc": "heddle.api.v1alpha1.RegistryService/UpdateNamespace",
      "capability": "spool administration",
      "layers": {
        "implementation": {
          "status": "shipped",
          "evidence": [
            "crates/weft-server/src/server/grpc_hosted_impl/user.rs:UpdateNamespace"
          ],
          "follow_up": null
        },
        "registration": {
          "status": "shipped",
          "evidence": [
            "crates/weft-server/src/serve.rs:HostedUserServiceServer::new"
          ],
          "follow_up": null
        }
      }
    },
    {
      "rpc": "heddle.api.v1alpha1.RegistryService/UpdateRepository",
      "capability": "spool administration",
      "layers": {
        "implementation": {
          "status": "shipped",
          "evidence": [
            "crates/weft-server/src/server/grpc_hosted_impl/user.rs:UpdateRepository"
          ],
          "follow_up": null
        },
        "registration": {
          "status": "shipped",
          "evidence": [
            "crates/weft-server/src/serve.rs:HostedUserServiceServer::new"
          ],
          "follow_up": null
        }
      }
    },
    {
      "rpc": "heddle.api.v1alpha1.RegistryService/UpdateSpoolSettings",
      "capability": "spool administration",
      "layers": {
        "implementation": {
          "status": "shipped",
          "evidence": [
            "crates/weft-server/src/server/grpc_hosted_impl/user.rs:UpdateSpoolSettings"
          ],
          "follow_up": null
        },
        "registration": {
          "status": "shipped",
          "evidence": [
            "crates/weft-server/src/serve.rs:HostedUserServiceServer::new"
          ],
          "follow_up": null
        }
      }
    },
    {
      "rpc": "heddle.api.v1alpha1.RegistryService/UpsertBookmark",
      "capability": "spool administration",
      "layers": {
        "implementation": {
          "status": "shipped",
          "evidence": [
            "crates/weft-server/src/server/grpc_hosted_impl/user.rs:UpsertBookmark"
          ],
          "follow_up": null
        },
        "registration": {
          "status": "shipped",
          "evidence": [
            "crates/weft-server/src/serve.rs:HostedUserServiceServer::new"
          ],
          "follow_up": null
        }
      }
    },
    {
      "rpc": "heddle.api.v1alpha1.RepoSyncService/ListRefs",
      "capability": "synchronization",
      "layers": {
        "implementation": {
          "status": "shipped",
          "evidence": [
            "crates/weft-server/src/server/grpc_hosted_impl/sync.rs:ListRefs"
          ],
          "follow_up": null
        },
        "registration": {
          "status": "shipped",
          "evidence": [
            "crates/weft-server/src/serve.rs:RepoSyncServiceServer::new"
          ],
          "follow_up": null
        }
      }
    },
    {
      "rpc": "heddle.api.v1alpha1.RepoSyncService/Pull",
      "capability": "synchronization",
      "layers": {
        "implementation": {
          "status": "shipped",
          "evidence": [
            "crates/weft-server/src/server/grpc_hosted_impl/sync.rs:Pull"
          ],
          "follow_up": null
        },
        "registration": {
          "status": "shipped",
          "evidence": [
            "crates/weft-server/src/serve.rs:RepoSyncServiceServer::new"
          ],
          "follow_up": null
        }
      }
    },
    {
      "rpc": "heddle.api.v1alpha1.RepoSyncService/Push",
      "capability": "synchronization",
      "layers": {
        "implementation": {
          "status": "shipped",
          "evidence": [
            "crates/weft-server/src/server/grpc_hosted_impl/sync.rs:Push"
          ],
          "follow_up": null
        },
        "registration": {
          "status": "shipped",
          "evidence": [
            "crates/weft-server/src/serve.rs:RepoSyncServiceServer::new"
          ],
          "follow_up": null
        }
      }
    },
    {
      "rpc": "heddle.api.v1alpha1.RepoSyncService/UpdateRef",
      "capability": "synchronization",
      "layers": {
        "implementation": {
          "status": "shipped",
          "evidence": [
            "crates/weft-server/src/server/grpc_hosted_impl/sync.rs:UpdateRef"
          ],
          "follow_up": null
        },
        "registration": {
          "status": "shipped",
          "evidence": [
            "crates/weft-server/src/serve.rs:RepoSyncServiceServer::new"
          ],
          "follow_up": null
        }
      }
    },
    {
      "rpc": "heddle.api.v1alpha1.RepositoryService/CreateImportJob",
      "capability": "repository inspection",
      "layers": {
        "implementation": {
          "status": "shipped",
          "evidence": [
            "crates/weft-server/src/server/grpc_hosted_impl/import.rs:CreateImportJob"
          ],
          "follow_up": null
        },
        "registration": {
          "status": "shipped",
          "evidence": [
            "crates/weft-server/src/serve.rs:ImportServiceServer::new"
          ],
          "follow_up": null
        }
      }
    },
    {
      "rpc": "heddle.api.v1alpha1.RepositoryService/GetBlame",
      "capability": "repository inspection",
      "layers": {
        "implementation": {
          "status": "shipped",
          "evidence": [
            "crates/weft-server/src/server/grpc_hosted_impl/content.rs:GetBlame"
          ],
          "follow_up": null
        },
        "registration": {
          "status": "shipped",
          "evidence": [
            "crates/weft-server/src/serve.rs:ContentServiceServer::new"
          ],
          "follow_up": null
        }
      }
    },
    {
      "rpc": "heddle.api.v1alpha1.RepositoryService/GetBlob",
      "capability": "repository inspection",
      "layers": {
        "implementation": {
          "status": "shipped",
          "evidence": [
            "crates/weft-server/src/server/grpc_hosted_impl/content.rs:GetBlob"
          ],
          "follow_up": null
        },
        "registration": {
          "status": "shipped",
          "evidence": [
            "crates/weft-server/src/serve.rs:ContentServiceServer::new"
          ],
          "follow_up": null
        }
      }
    },
    {
      "rpc": "heddle.api.v1alpha1.RepositoryService/GetCompare",
      "capability": "state comparison",
      "layers": {
        "implementation": {
          "status": "shipped",
          "evidence": [
            "crates/weft-server/src/server/grpc_hosted_impl/content.rs:GetCompare"
          ],
          "follow_up": null
        },
        "registration": {
          "status": "shipped",
          "evidence": [
            "crates/weft-server/src/serve.rs:ContentServiceServer::new"
          ],
          "follow_up": null
        }
      }
    },
    {
      "rpc": "heddle.api.v1alpha1.RepositoryService/GetContextHistory",
      "capability": "repository inspection",
      "layers": {
        "implementation": {
          "status": "shipped",
          "evidence": [
            "crates/weft-server/src/server/grpc_hosted_impl/content.rs:GetContextHistory"
          ],
          "follow_up": null
        },
        "registration": {
          "status": "shipped",
          "evidence": [
            "crates/weft-server/src/serve.rs:ContentServiceServer::new"
          ],
          "follow_up": null
        }
      }
    },
    {
      "rpc": "heddle.api.v1alpha1.RepositoryService/GetDiff",
      "capability": "repository inspection",
      "layers": {
        "implementation": {
          "status": "shipped",
          "evidence": [
            "crates/weft-server/src/server/grpc_hosted_impl/content.rs:GetDiff"
          ],
          "follow_up": null
        },
        "registration": {
          "status": "shipped",
          "evidence": [
            "crates/weft-server/src/serve.rs:ContentServiceServer::new"
          ],
          "follow_up": null
        }
      }
    },
    {
      "rpc": "heddle.api.v1alpha1.RepositoryService/GetRefs",
      "capability": "repository inspection",
      "layers": {
        "implementation": {
          "status": "shipped",
          "evidence": [
            "crates/weft-server/src/server/grpc_hosted_impl/content.rs:GetRefs"
          ],
          "follow_up": null
        },
        "registration": {
          "status": "shipped",
          "evidence": [
            "crates/weft-server/src/serve.rs:ContentServiceServer::new"
          ],
          "follow_up": null
        }
      }
    },
    {
      "rpc": "heddle.api.v1alpha1.RepositoryService/GetSemanticHotSpots",
      "capability": "repository inspection",
      "layers": {
        "implementation": {
          "status": "shipped",
          "evidence": [
            "crates/weft-server/src/server/grpc_hosted_impl/content.rs:GetSemanticHotSpots"
          ],
          "follow_up": null
        },
        "registration": {
          "status": "shipped",
          "evidence": [
            "crates/weft-server/src/serve.rs:ContentServiceServer::new"
          ],
          "follow_up": null
        }
      }
    },
    {
      "rpc": "heddle.api.v1alpha1.RepositoryService/GetState",
      "capability": "run history/details",
      "layers": {
        "implementation": {
          "status": "shipped",
          "evidence": [
            "crates/weft-server/src/server/grpc_hosted_impl/content.rs:GetState"
          ],
          "follow_up": null
        },
        "registration": {
          "status": "shipped",
          "evidence": [
            "crates/weft-server/src/serve.rs:ContentServiceServer::new"
          ],
          "follow_up": null
        }
      }
    },
    {
      "rpc": "heddle.api.v1alpha1.RepositoryService/GetTree",
      "capability": "repository inspection",
      "layers": {
        "implementation": {
          "status": "shipped",
          "evidence": [
            "crates/weft-server/src/server/grpc_hosted_impl/content.rs:GetTree"
          ],
          "follow_up": null
        },
        "registration": {
          "status": "shipped",
          "evidence": [
            "crates/weft-server/src/serve.rs:ContentServiceServer::new"
          ],
          "follow_up": null
        }
      }
    },
    {
      "rpc": "heddle.api.v1alpha1.RepositoryService/ListActions",
      "capability": "repository inspection",
      "layers": {
        "implementation": {
          "status": "shipped",
          "evidence": [
            "crates/weft-server/src/server/grpc_hosted_impl/content.rs:ListActions"
          ],
          "follow_up": null
        },
        "registration": {
          "status": "shipped",
          "evidence": [
            "crates/weft-server/src/serve.rs:ContentServiceServer::new"
          ],
          "follow_up": null
        }
      }
    },
    {
      "rpc": "heddle.api.v1alpha1.RepositoryService/ListContext",
      "capability": "repository inspection",
      "layers": {
        "implementation": {
          "status": "shipped",
          "evidence": [
            "crates/weft-server/src/server/grpc_hosted_impl/content.rs:ListContext"
          ],
          "follow_up": null
        },
        "registration": {
          "status": "shipped",
          "evidence": [
            "crates/weft-server/src/serve.rs:ContentServiceServer::new"
          ],
          "follow_up": null
        }
      }
    },
    {
      "rpc": "heddle.api.v1alpha1.RepositoryService/ListContextSuggestions",
      "capability": "repository inspection",
      "layers": {
        "implementation": {
          "status": "shipped",
          "evidence": [
            "crates/weft-server/src/server/grpc_hosted_impl/content.rs:ListContextSuggestions"
          ],
          "follow_up": null
        },
        "registration": {
          "status": "shipped",
          "evidence": [
            "crates/weft-server/src/serve.rs:ContentServiceServer::new"
          ],
          "follow_up": null
        }
      }
    },
    {
      "rpc": "heddle.api.v1alpha1.RepositoryService/ListProvenanceSummaries",
      "capability": "repository inspection",
      "layers": {
        "implementation": {
          "status": "shipped",
          "evidence": [
            "crates/weft-server/src/server/grpc_hosted_impl/content.rs:ListProvenanceSummaries"
          ],
          "follow_up": null
        },
        "registration": {
          "status": "shipped",
          "evidence": [
            "crates/weft-server/src/serve.rs:ContentServiceServer::new"
          ],
          "follow_up": null
        }
      }
    },
    {
      "rpc": "heddle.api.v1alpha1.RepositoryService/ListStates",
      "capability": "run history/details",
      "layers": {
        "implementation": {
          "status": "shipped",
          "evidence": [
            "crates/weft-server/src/server/grpc_hosted_impl/content.rs:ListStates"
          ],
          "follow_up": null
        },
        "registration": {
          "status": "shipped",
          "evidence": [
            "crates/weft-server/src/serve.rs:ContentServiceServer::new"
          ],
          "follow_up": null
        }
      }
    },
    {
      "rpc": "heddle.api.v1alpha1.RepositoryService/ReviseContext",
      "capability": "repository inspection",
      "layers": {
        "implementation": {
          "status": "shipped",
          "evidence": [
            "crates/weft-server/src/server/grpc_hosted_impl/content.rs:ReviseContext"
          ],
          "follow_up": null
        },
        "registration": {
          "status": "shipped",
          "evidence": [
            "crates/weft-server/src/serve.rs:ContentServiceServer::new"
          ],
          "follow_up": null
        }
      }
    },
    {
      "rpc": "heddle.api.v1alpha1.RepositoryService/SetContext",
      "capability": "repository inspection",
      "layers": {
        "implementation": {
          "status": "shipped",
          "evidence": [
            "crates/weft-server/src/server/grpc_hosted_impl/content.rs:SetContext"
          ],
          "follow_up": null
        },
        "registration": {
          "status": "shipped",
          "evidence": [
            "crates/weft-server/src/serve.rs:ContentServiceServer::new"
          ],
          "follow_up": null
        }
      }
    },
    {
      "rpc": "heddle.api.v1alpha1.RepositoryService/StreamImportProgress",
      "capability": "repository inspection",
      "layers": {
        "implementation": {
          "status": "shipped",
          "evidence": [
            "crates/weft-server/src/server/grpc_hosted_impl/import.rs:StreamImportProgress"
          ],
          "follow_up": null
        },
        "registration": {
          "status": "shipped",
          "evidence": [
            "crates/weft-server/src/serve.rs:ImportServiceServer::new"
          ],
          "follow_up": null
        }
      }
    },
    {
      "rpc": "heddle.api.v1alpha1.RepositoryService/SubscribeRepoEvents",
      "capability": "repository inspection",
      "layers": {
        "implementation": {
          "status": "shipped",
          "evidence": [
            "crates/weft-server/src/server/grpc_hosted_impl/events.rs:SubscribeRepoEvents"
          ],
          "follow_up": null
        },
        "registration": {
          "status": "shipped",
          "evidence": [
            "crates/weft-server/src/serve.rs:RepoEventServiceServer::new"
          ],
          "follow_up": null
        }
      }
    },
    {
      "rpc": "heddle.api.v1alpha1.RepositoryService/SupersedeContext",
      "capability": "repository inspection",
      "layers": {
        "implementation": {
          "status": "shipped",
          "evidence": [
            "crates/weft-server/src/server/grpc_hosted_impl/content.rs:SupersedeContext"
          ],
          "follow_up": null
        },
        "registration": {
          "status": "shipped",
          "evidence": [
            "crates/weft-server/src/serve.rs:ContentServiceServer::new"
          ],
          "follow_up": null
        }
      }
    },
    {
      "rpc": "heddle.api.v1alpha1.SearchService/Search",
      "capability": "search",
      "layers": {
        "implementation": {
          "status": "shipped",
          "evidence": [
            "crates/weft-server/src/server/grpc_hosted_impl/search.rs:Search"
          ],
          "follow_up": null
        },
        "registration": {
          "status": "shipped",
          "evidence": [
            "crates/weft-server/src/serve.rs:SearchServiceServer::new"
          ],
          "follow_up": null
        }
      }
    },
    {
      "rpc": "heddle.api.v1alpha1.StateReviewService/GetReviewPayload",
      "capability": "review decisions",
      "layers": {
        "implementation": {
          "status": "shipped",
          "evidence": [
            "crates/weft-server/src/server/grpc_hosted_impl/state_review.rs:GetReviewPayload"
          ],
          "follow_up": null
        },
        "registration": {
          "status": "shipped",
          "evidence": [
            "crates/weft-server/src/serve.rs:StateReviewServiceServer::new"
          ],
          "follow_up": null
        }
      }
    },
    {
      "rpc": "heddle.api.v1alpha1.StateReviewService/ListSignatures",
      "capability": "review decisions",
      "layers": {
        "implementation": {
          "status": "shipped",
          "evidence": [
            "crates/weft-server/src/server/grpc_hosted_impl/state_review.rs:ListSignatures"
          ],
          "follow_up": null
        },
        "registration": {
          "status": "shipped",
          "evidence": [
            "crates/weft-server/src/serve.rs:StateReviewServiceServer::new"
          ],
          "follow_up": null
        }
      }
    },
    {
      "rpc": "heddle.api.v1alpha1.StateReviewService/SignState",
      "capability": "review decisions",
      "layers": {
        "implementation": {
          "status": "shipped",
          "evidence": [
            "crates/weft-server/src/server/grpc_hosted_impl/state_review.rs:SignState"
          ],
          "follow_up": null
        },
        "registration": {
          "status": "shipped",
          "evidence": [
            "crates/weft-server/src/serve.rs:StateReviewServiceServer::new"
          ],
          "follow_up": null
        }
      }
    },
    {
      "rpc": "heddle.api.v1alpha1.WorkflowService/AddApprovalGroupMember",
      "capability": "branch protection",
      "layers": {
        "implementation": {
          "status": "shipped",
          "evidence": [
            "crates/weft-server/src/server/grpc_hosted_impl/user.rs:AddApprovalGroupMember"
          ],
          "follow_up": null
        },
        "registration": {
          "status": "shipped",
          "evidence": [
            "crates/weft-server/src/serve.rs:HostedUserServiceServer::new"
          ],
          "follow_up": null
        }
      }
    },
    {
      "rpc": "heddle.api.v1alpha1.WorkflowService/AddPolicyGroupRequirement",
      "capability": "branch protection",
      "layers": {
        "implementation": {
          "status": "shipped",
          "evidence": [
            "crates/weft-server/src/server/grpc_hosted_impl/user.rs:AddPolicyGroupRequirement"
          ],
          "follow_up": null
        },
        "registration": {
          "status": "shipped",
          "evidence": [
            "crates/weft-server/src/serve.rs:HostedUserServiceServer::new"
          ],
          "follow_up": null
        }
      }
    },
    {
      "rpc": "heddle.api.v1alpha1.WorkflowService/ApproveThread",
      "capability": "branch protection",
      "layers": {
        "implementation": {
          "status": "shipped",
          "evidence": [
            "crates/weft-server/src/server/grpc_hosted_impl/user.rs:ApproveThread"
          ],
          "follow_up": null
        },
        "registration": {
          "status": "shipped",
          "evidence": [
            "crates/weft-server/src/serve.rs:HostedUserServiceServer::new"
          ],
          "follow_up": null
        }
      }
    },
    {
      "rpc": "heddle.api.v1alpha1.WorkflowService/CheckMergeEligibility",
      "capability": "branch protection",
      "layers": {
        "implementation": {
          "status": "shipped",
          "evidence": [
            "crates/weft-server/src/server/grpc_hosted_impl/user.rs:CheckMergeEligibility"
          ],
          "follow_up": null
        },
        "registration": {
          "status": "shipped",
          "evidence": [
            "crates/weft-server/src/serve.rs:HostedUserServiceServer::new"
          ],
          "follow_up": null
        }
      }
    },
    {
      "rpc": "heddle.api.v1alpha1.WorkflowService/CreateApprovalGroup",
      "capability": "branch protection",
      "layers": {
        "implementation": {
          "status": "shipped",
          "evidence": [
            "crates/weft-server/src/server/grpc_hosted_impl/user.rs:CreateApprovalGroup"
          ],
          "follow_up": null
        },
        "registration": {
          "status": "shipped",
          "evidence": [
            "crates/weft-server/src/serve.rs:HostedUserServiceServer::new"
          ],
          "follow_up": null
        }
      }
    },
    {
      "rpc": "heddle.api.v1alpha1.WorkflowService/CreateThreadPolicy",
      "capability": "branch protection",
      "layers": {
        "implementation": {
          "status": "shipped",
          "evidence": [
            "crates/weft-server/src/server/grpc_hosted_impl/user.rs:CreateThreadPolicy"
          ],
          "follow_up": null
        },
        "registration": {
          "status": "shipped",
          "evidence": [
            "crates/weft-server/src/serve.rs:HostedUserServiceServer::new"
          ],
          "follow_up": null
        }
      }
    },
    {
      "rpc": "heddle.api.v1alpha1.WorkflowService/DeleteApprovalGroup",
      "capability": "branch protection",
      "layers": {
        "implementation": {
          "status": "shipped",
          "evidence": [
            "crates/weft-server/src/server/grpc_hosted_impl/user.rs:DeleteApprovalGroup"
          ],
          "follow_up": null
        },
        "registration": {
          "status": "shipped",
          "evidence": [
            "crates/weft-server/src/serve.rs:HostedUserServiceServer::new"
          ],
          "follow_up": null
        }
      }
    },
    {
      "rpc": "heddle.api.v1alpha1.WorkflowService/DeleteThreadPolicy",
      "capability": "branch protection",
      "layers": {
        "implementation": {
          "status": "shipped",
          "evidence": [
            "crates/weft-server/src/server/grpc_hosted_impl/user.rs:DeleteThreadPolicy"
          ],
          "follow_up": null
        },
        "registration": {
          "status": "shipped",
          "evidence": [
            "crates/weft-server/src/serve.rs:HostedUserServiceServer::new"
          ],
          "follow_up": null
        }
      }
    },
    {
      "rpc": "heddle.api.v1alpha1.WorkflowService/GetWorkspaceSummary",
      "capability": "workspace management",
      "layers": {
        "implementation": {
          "status": "shipped",
          "evidence": [
            "crates/weft-server/src/server/grpc_hosted_impl/workflow.rs:GetWorkspaceSummary"
          ],
          "follow_up": null
        },
        "registration": {
          "status": "shipped",
          "evidence": [
            "crates/weft-server/src/serve.rs:ThreadWorkflowServiceServer::new"
          ],
          "follow_up": null
        }
      }
    },
    {
      "rpc": "heddle.api.v1alpha1.WorkflowService/ListApprovalGroups",
      "capability": "branch protection",
      "layers": {
        "implementation": {
          "status": "shipped",
          "evidence": [
            "crates/weft-server/src/server/grpc_hosted_impl/user.rs:ListApprovalGroups"
          ],
          "follow_up": null
        },
        "registration": {
          "status": "shipped",
          "evidence": [
            "crates/weft-server/src/serve.rs:HostedUserServiceServer::new"
          ],
          "follow_up": null
        }
      }
    },
    {
      "rpc": "heddle.api.v1alpha1.WorkflowService/ListThreadApprovals",
      "capability": "branch protection",
      "layers": {
        "implementation": {
          "status": "shipped",
          "evidence": [
            "crates/weft-server/src/server/grpc_hosted_impl/user.rs:ListThreadApprovals"
          ],
          "follow_up": null
        },
        "registration": {
          "status": "shipped",
          "evidence": [
            "crates/weft-server/src/serve.rs:HostedUserServiceServer::new"
          ],
          "follow_up": null
        }
      }
    },
    {
      "rpc": "heddle.api.v1alpha1.WorkflowService/ListThreadPolicies",
      "capability": "branch protection",
      "layers": {
        "implementation": {
          "status": "shipped",
          "evidence": [
            "crates/weft-server/src/server/grpc_hosted_impl/user.rs:ListThreadPolicies"
          ],
          "follow_up": null
        },
        "registration": {
          "status": "shipped",
          "evidence": [
            "crates/weft-server/src/serve.rs:HostedUserServiceServer::new"
          ],
          "follow_up": null
        }
      }
    },
    {
      "rpc": "heddle.api.v1alpha1.WorkflowService/ListThreads",
      "capability": "workspace management",
      "layers": {
        "implementation": {
          "status": "shipped",
          "evidence": [
            "crates/weft-server/src/server/grpc_hosted_impl/workflow.rs:ListThreads"
          ],
          "follow_up": null
        },
        "registration": {
          "status": "shipped",
          "evidence": [
            "crates/weft-server/src/serve.rs:ThreadWorkflowServiceServer::new"
          ],
          "follow_up": null
        }
      }
    },
    {
      "rpc": "heddle.api.v1alpha1.WorkflowService/RemoveApprovalGroupMember",
      "capability": "branch protection",
      "layers": {
        "implementation": {
          "status": "shipped",
          "evidence": [
            "crates/weft-server/src/server/grpc_hosted_impl/user.rs:RemoveApprovalGroupMember"
          ],
          "follow_up": null
        },
        "registration": {
          "status": "shipped",
          "evidence": [
            "crates/weft-server/src/serve.rs:HostedUserServiceServer::new"
          ],
          "follow_up": null
        }
      }
    },
    {
      "rpc": "heddle.api.v1alpha1.WorkflowService/RemovePolicyGroupRequirement",
      "capability": "branch protection",
      "layers": {
        "implementation": {
          "status": "shipped",
          "evidence": [
            "crates/weft-server/src/server/grpc_hosted_impl/user.rs:RemovePolicyGroupRequirement"
          ],
          "follow_up": null
        },
        "registration": {
          "status": "shipped",
          "evidence": [
            "crates/weft-server/src/serve.rs:HostedUserServiceServer::new"
          ],
          "follow_up": null
        }
      }
    },
    {
      "rpc": "heddle.api.v1alpha1.WorkflowService/RevokeApproval",
      "capability": "branch protection",
      "layers": {
        "implementation": {
          "status": "shipped",
          "evidence": [
            "crates/weft-server/src/server/grpc_hosted_impl/user.rs:RevokeApproval"
          ],
          "follow_up": null
        },
        "registration": {
          "status": "shipped",
          "evidence": [
            "crates/weft-server/src/serve.rs:HostedUserServiceServer::new"
          ],
          "follow_up": null
        }
      }
    },
    {
      "rpc": "heddle.api.v1alpha1.WorkflowService/StreamWorkspaceSummary",
      "capability": "workspace management",
      "layers": {
        "implementation": {
          "status": "shipped",
          "evidence": [
            "crates/weft-server/src/server/grpc_hosted_impl/workflow.rs:StreamWorkspaceSummary"
          ],
          "follow_up": null
        },
        "registration": {
          "status": "shipped",
          "evidence": [
            "crates/weft-server/src/serve.rs:ThreadWorkflowServiceServer::new"
          ],
          "follow_up": null
        }
      }
    }
  ]
}
